{
  "phase": "10Y.0",
  "module": "Enterprise Master Registry and Digital Twin",
  "timestamp": "2026-06-19T07:51:05.221Z",
  "status": "PASS",
  "passed": 10,
  "failed": 0,
  "checks": [
    {
      "name": "Master Registry Exists",
      "pass": true
    },
    {
      "name": "Digital Twin Exists",
      "pass": true
    },
    {
      "name": "Engine Registry Exists",
      "pass": true
    },
    {
      "name": "Route Registry Exists",
      "pass": true
    },
    {
      "name": "Endpoint Registry Exists",
      "pass": true
    },
    {
      "name": "Dependency Graph Exists",
      "pass": true
    },
    {
      "name": "Impact Analysis Exists",
      "pass": true
    },
    {
      "name": "Technical Debt Scan Exists",
      "pass": true
    },
    {
      "name": "Industrial Court Registry Exists",
      "pass": true
    },
    {
      "name": "PERKESO Registry Exists",
      "pass": true
    }
  ],
  "twinSummary": {
    "engines": 38,
    "routes": 57,
    "endpoints": 279,
    "workflows": 10,
    "dashboards": 10,
    "documents": 271,
    "integrations": 6,
    "courts": 6,
    "industrialCourts": 1,
    "perkesoOffices": 2
  },
  "deployment": {
    "registry": "deployment-registry",
    "generatedAt": "2026-06-19T07:51:05.170Z",
    "scoringAvailable": true,
    "gatekeeperAvailable": true,
    "governanceAvailable": true,
    "latestScore": 100,
    "latestGrade": "A+",
    "latestRisk": "LOW",
    "gatekeeperStatus": "APPROVED",
    "deploymentApproved": true
  }
}